{"page":512,"lines":[{"type":"ayah","line":1,"words":[{"id":70584,"a":"إِنَّ","m":"Indeed","mi":"sesungguhnya","mu":"بیشک","t":"inna","s":48,"v":10,"w":1,"li":4098},{"id":70585,"a":"ٱلَّذِينَ","m":"those who","mi":"orang-orang yang","mu":"وہ لوگ","t":"alladhīna","s":48,"v":10,"w":2,"li":2297},{"id":70586,"a":"يُبَايِعُونَكَ","m":"pledge allegiance to you","mi":"mereka berjanji setia kepadamu","mu":"جنہوں نے بیعت کی آپ کی۔ جو بیعت کر رہے ہیں آپ کی","t":"yubāyiʿūnaka","s":48,"v":10,"w":3,"ri":707,"li":56},{"id":70587,"a":"إِنَّمَا","m":"only","mi":"sesungguhnya hanyalah","mu":"بیشک","t":"innamā","s":48,"v":10,"w":4,"li":4098},{"id":70588,"a":"يُبَايِعُونَ","m":"they pledge allegiance","mi":"mereka berjanji setia","mu":"وہ بیعت کر رہے ہیں۔ انہوں نے بیعت کی","t":"yubāyiʿūna","s":48,"v":10,"w":5,"ri":707,"li":56},{"id":70589,"a":"ٱللَّهَ","m":"(to) Allah","mi":"Allah","mu":"اللہ سے","t":"l-laha","s":48,"v":10,"w":6,"ri":1217,"li":2564},{"id":70590,"a":"يَدُ","m":"(The) Hand","mi":"tangan","mu":"ہاتھ تھا","t":"yadu","s":48,"v":10,"w":7,"ri":1254,"li":4264},{"id":70591,"a":"ٱللَّهِ","m":"(of) Allah","mi":"Allah","mu":"اللہ کا","t":"l-lahi","s":48,"v":10,"w":8,"ri":1217,"li":2564},{"id":70592,"a":"فَوۡقَ","m":"(is) over","mi":"di atas","mu":"اوپر ہے","t":"fawqa","s":48,"v":10,"w":9,"ri":42,"li":870}]},{"type":"ayah","line":2,"words":[{"id":70593,"a":"أَيۡدِيهِمۡۚ","m":"their hands","mi":"tangan mereka","mu":"ان کے ہاتھ پر","t":"aydīhim","s":48,"v":10,"w":10,"ri":1254,"li":4264},{"id":70594,"a":"فَمَن","m":"Then whoever","mi":"maka barang siapa","mu":"تو جو کوئی","t":"faman","s":48,"v":10,"w":11,"li":477},{"id":70595,"a":"نَّكَثَ","m":"breaks (his oath)","mi":"melanggar janji","mu":"توڑ دے","t":"nakatha","s":48,"v":10,"w":12,"ri":1230,"li":3413},{"id":70596,"a":"فَإِنَّمَا","m":"then only","mi":"maka sesungguhnya hanyalah","mu":"تو بیشک","t":"fa-innamā","s":48,"v":10,"w":13,"li":4098},{"id":70597,"a":"يَنكُثُ","m":"he breaks","mi":"dia melanggar","mu":"وہ توڑتا ہے","t":"yankuthu","s":48,"v":10,"w":14,"ri":1230,"li":3413},{"id":70598,"a":"عَلَىٰ","m":"against","mi":"atas","mu":"پر","t":"ʿalā","s":48,"v":10,"w":15,"li":1100},{"id":70599,"a":"نَفۡسِهِۦۖ","m":"himself","mi":"dirinya","mu":"اپنے نفس","t":"nafsihi","s":48,"v":10,"w":16,"ri":1140},{"id":70600,"a":"وَمَنۡ","m":"and whoever","mi":"dan barang siapa","mu":"اور جو کوئی","t":"waman","s":48,"v":10,"w":17,"li":477},{"id":70601,"a":"أَوۡفَىٰ","m":"fulfils","mi":"menepati","mu":"پورا کرے","t":"awfā","s":48,"v":10,"w":18,"ri":814}]},{"type":"ayah","line":3,"words":[{"id":70602,"a":"بِمَا","m":"what","mi":"dengan apa","mu":"اس کو جو","t":"bimā","s":48,"v":10,"w":19,"li":4506},{"id":70603,"a":"عَٰهَدَ","m":"he has covenanted","mi":"berjanji","mu":"اس نے عہد کیا","t":"ʿāhada","s":48,"v":10,"w":20,"ri":1324,"li":603},{"id":70604,"a":"عَلَيۡهُ","m":"(with)","mi":"atasnya","mu":"اس پر","t":"ʿalayhu","s":48,"v":10,"w":21,"li":1100},{"id":70605,"a":"ٱللَّهَ","m":"Allah","mi":"Allah","mu":"اللہ سے","t":"l-laha","s":48,"v":10,"w":22,"ri":1217,"li":2564},{"id":70606,"a":"فَسَيُؤۡتِيهِ","m":"soon He will give him","mi":"maka Dia akan memberinya","mu":"تو عنقریب وہ دے گا اس کو","t":"fasayu'tīhi","s":48,"v":10,"w":23,"ri":1311},{"id":70607,"a":"أَجۡرًا","m":"a reward","mi":"pahala","mu":"اجر","t":"ajran","s":48,"v":10,"w":24,"ri":804,"li":3255},{"id":70608,"a":"عَظِيمٗا","m":"great","mi":"besar","mu":"عظیم","t":"ʿaẓīman","s":48,"v":10,"w":25,"ri":571,"li":1194},{"id":70609,"a":"١٠","m":"(10)","mi":"(10)","mu":"(۱۰)","t":"","s":48,"v":10,"w":26},{"id":70610,"a":"سَيَقُولُ","m":"Will say","mi":"akan mengatakan","mu":"عنقریب کہیں گے","t":"sayaqūlu","s":48,"v":11,"w":1,"ri":23,"li":1981}]},{"type":"ayah","line":4,"words":[{"id":70611,"a":"لَكَ","m":"to you","mi":"kepadamu","mu":"آپ کو","t":"laka","s":48,"v":11,"w":2},{"id":70612,"a":"ٱلۡمُخَلَّفُونَ","m":"those who remained behind","mi":"mereka tertinggal","mu":"پیچھے چھوڑے جانے والے۔ پیچھے رہ جانے والے","t":"l-mukhalafūna","s":48,"v":11,"w":3,"ri":1277,"li":3655},{"id":70613,"a":"مِنَ","m":"of","mi":"dari","mu":"سے","t":"mina","s":48,"v":11,"w":4,"li":477},{"id":70614,"a":"ٱلۡأَعۡرَابِ","m":"the Bedouins","mi":"orang-orang arab dusun","mu":"بدوؤں میں (سے)","t":"l-aʿrābi","s":48,"v":11,"w":5,"ri":1318,"li":1401},{"id":70615,"a":"شَغَلَتۡنَآ","m":"Kept us busy","mi":"telah menyibukkan kami","mu":"مشغول کیا تھا ہم کو","t":"shaghalatnā","s":48,"v":11,"w":6,"ri":872,"li":617},{"id":70616,"a":"أَمۡوَٰلُنَا","m":"our properties","mi":"harta kami","mu":"ہمارے مالوں نے","t":"amwālunā","s":48,"v":11,"w":7,"ri":333,"li":2358},{"id":70617,"a":"وَأَهۡلُونَا","m":"and our families","mi":"dan keluarga kami","mu":"اور ہمارے اہل و عیال نے","t":"wa-ahlūnā","s":48,"v":11,"w":8,"ri":1524,"li":4719}]},{"type":"ayah","line":5,"words":[{"id":70618,"a":"فَٱسۡتَغۡفِرۡ","m":"so ask forgiveness","mi":"maka mohon ampunan","mu":"پس بخشش مانگیئے","t":"fa-is'taghfir","s":48,"v":11,"w":9,"ri":1260,"li":3993},{"id":70619,"a":"لَنَاۚ","m":"for us","mi":"bagi kami","mu":"ہمارے لیے","t":"lanā","s":48,"v":11,"w":10},{"id":70620,"a":"يَقُولُونَ","m":"They say","mi":"mereka berkata","mu":"وہ کہتے ہیں","t":"yaqūlūna","s":48,"v":11,"w":11,"ri":23,"li":1981},{"id":70621,"a":"بِأَلۡسِنَتِهِم","m":"with their tongues","mi":"dengan lisan mereka","mu":"اپنی زبانوں کے ساتھ","t":"bi-alsinatihim","s":48,"v":11,"w":12,"ri":197,"li":4448},{"id":70622,"a":"مَّا","m":"what","mi":"apa yang","mu":"جو","t":"mā","s":48,"v":11,"w":13,"li":4506},{"id":70623,"a":"لَيۡسَ","m":"is not","mi":"tidak ada","mu":"نہیں","t":"laysa","s":48,"v":11,"w":14,"ri":419,"li":4591},{"id":70624,"a":"فِي","m":"in","mi":"dalam","mu":"میں","t":"fī","s":48,"v":11,"w":15,"li":3504},{"id":70625,"a":"قُلُوبِهِمۡۚ","m":"their hearts","mi":"hati mereka","mu":"ان کے دلوں (میں)","t":"qulūbihim","s":48,"v":11,"w":16,"ri":582,"li":4417},{"id":70626,"a":"قُلۡ","m":"Say","mi":"katakanlah","mu":"کہہ دیجیے","t":"qul","s":48,"v":11,"w":17,"ri":23,"li":1981}]},{"type":"ayah","line":6,"words":[{"id":70627,"a":"فَمَن","m":"Then who","mi":"maka siapakah","mu":"پس کون","t":"faman","s":48,"v":11,"w":18,"li":477},{"id":70628,"a":"يَمۡلِكُ","m":"has power","mi":"memiliki/kuasa","mu":"مالک ہوگا","t":"yamliku","s":48,"v":11,"w":19,"ri":1236,"li":1012},{"id":70629,"a":"لَكُم","m":"for you","mi":"bagi kalian","mu":"تمہارے لیے","t":"lakum","s":48,"v":11,"w":20},{"id":70630,"a":"مِّنَ","m":"against","mi":"dari","mu":"سے","t":"mina","s":48,"v":11,"w":21,"li":477},{"id":70631,"a":"ٱللَّهِ","m":"Allah","mi":"Allah","mu":"اللہ","t":"l-lahi","s":48,"v":11,"w":22,"ri":1217,"li":2564},{"id":70632,"a":"شَيۡـًٔا","m":"(in) anything","mi":"sedikitpun","mu":"کسی چیز کا","t":"shayan","s":48,"v":11,"w":23,"ri":1485},{"id":70633,"a":"إِنۡ","m":"if","mi":"jika","mu":"اگر","t":"in","s":48,"v":11,"w":24,"li":3466},{"id":70634,"a":"أَرَادَ","m":"He intends","mi":"Dia menghendaki","mu":"اس نے ارادہ کیا","t":"arāda","s":48,"v":11,"w":25,"ri":189,"li":1261},{"id":70635,"a":"بِكُمۡ","m":"for you","mi":"dengan/untuk kalian","mu":"تمہارے ساتھ","t":"bikum","s":48,"v":11,"w":26},{"id":70636,"a":"ضَرًّا","m":"harm","mi":"mudharat/bahaya","mu":"نقصان کا","t":"ḍarran","s":48,"v":11,"w":27,"ri":704,"li":991},{"id":70637,"a":"أَوۡ","m":"or","mi":"atau","mu":"یا","t":"aw","s":48,"v":11,"w":28,"li":3499},{"id":70638,"a":"أَرَادَ","m":"He intends","mi":"Dia menghendaki","mu":"اس نے ارادہ کیا","t":"arāda","s":48,"v":11,"w":29,"ri":189,"li":1261},{"id":70639,"a":"بِكُمۡ","m":"for you","mi":"dengan/untuk kalian","mu":"تمہارے ساتھ","t":"bikum","s":48,"v":11,"w":30}]},{"type":"ayah","line":7,"words":[{"id":70640,"a":"نَفۡعَۢاۚ","m":"a benefit","mi":"manfaat","mu":"نفع کا","t":"nafʿan","s":48,"v":11,"w":31,"ri":506,"li":2476},{"id":70641,"a":"بَلۡ","m":"Nay","mi":"bahkan","mu":"بلکہ","t":"bal","s":48,"v":11,"w":32,"li":3119},{"id":70642,"a":"كَانَ","m":"is","mi":"adalah","mu":"ہے","t":"kāna","s":48,"v":11,"w":33,"ri":1021,"li":370},{"id":70643,"a":"ٱللَّهُ","m":"Allah","mi":"Allah","mu":"اللہ تعالیٰ","t":"l-lahu","s":48,"v":11,"w":34,"ri":1217,"li":2564},{"id":70644,"a":"بِمَا","m":"of what","mi":"terhadap apa","mu":"ساتھ اس کے جو","t":"bimā","s":48,"v":11,"w":35,"li":4506},{"id":70645,"a":"تَعۡمَلُونَ","m":"you do","mi":"kamu kerjakan","mu":"تم عمل کر رہے ہو","t":"taʿmalūna","s":48,"v":11,"w":36,"ri":757,"li":2119},{"id":70646,"a":"خَبِيرَۢا","m":"All-Aware","mi":"Maha Mengetahui","mu":"پورا باخبر","t":"khabīran","s":48,"v":11,"w":37,"ri":49,"li":3039},{"id":70647,"a":"١١","m":"(11)","mi":"(11)","mu":"(۱۱)","t":"","s":48,"v":11,"w":38},{"id":70648,"a":"بَلۡ","m":"Nay","mi":"bahkan/tetapi","mu":"بلکہ","t":"bal","s":48,"v":12,"w":1,"li":3119},{"id":70649,"a":"ظَنَنتُمۡ","m":"you thought","mi":"kamu telah menyangka","mu":"گمان کیا تم نے","t":"ẓanantum","s":48,"v":12,"w":2,"ri":913,"li":50},{"id":70650,"a":"أَن","m":"that","mi":"bahwa","mu":"کہ","t":"an","s":48,"v":12,"w":3,"li":1648},{"id":70651,"a":"لَّن","m":"(would) never","mi":"tidak akan","mu":"ہرگز نہیں","t":"lan","s":48,"v":12,"w":4,"li":2288}]},{"type":"ayah","line":8,"words":[{"id":70652,"a":"يَنقَلِبَ","m":"return","mi":"berbalik/kembali","mu":"پلٹ کر آئیں گے","t":"yanqaliba","s":48,"v":12,"w":5,"ri":582,"li":4777},{"id":70653,"a":"ٱلرَّسُولُ","m":"the Messenger","mi":"rasul","mu":"رسول (صلی اللہ علیہ وآلہ وسلم)","t":"l-rasūlu","s":48,"v":12,"w":6,"ri":656,"li":610},{"id":70654,"a":"وَٱلۡمُؤۡمِنُونَ","m":"and the believers","mi":"dan orang-orang mukmin","mu":"اور مومن","t":"wal-mu'minūna","s":48,"v":12,"w":7,"ri":537,"li":254},{"id":70655,"a":"إِلَىٰٓ","m":"to","mi":"kepada","mu":"طرف","t":"ilā","s":48,"v":12,"w":8,"li":3611},{"id":70656,"a":"أَهۡلِيهِمۡ","m":"their families","mi":"keluarga mereka","mu":"اپنے گھر والوں کی طرف","t":"ahlīhim","s":48,"v":12,"w":9,"ri":1524,"li":4719},{"id":70657,"a":"أَبَدٗا","m":"ever","mi":"selama-lamanya","mu":"کبھی بھی","t":"abadan","s":48,"v":12,"w":10,"ri":51,"li":547},{"id":70658,"a":"وَزُيِّنَ","m":"that was made fair-seeming","mi":"dan menjadikan memandang baik","mu":"اور خوبصورت بنادی گئی","t":"wazuyyina","s":48,"v":12,"w":11,"ri":1366,"li":3940},{"id":70659,"a":"ذَٰلِكَ","m":"that was made fair-seeming","mi":"demikian itu","mu":"یہ بات","t":"dhālika","s":48,"v":12,"w":12,"li":1167},{"id":70660,"a":"فِي","m":"in","mi":"dalam","mu":"میں","t":"fī","s":48,"v":12,"w":13,"li":3504}]},{"type":"ayah","line":9,"words":[{"id":70661,"a":"قُلُوبِكُمۡ","m":"your hearts","mi":"hatimu","mu":"تمہارے دلوں میں","t":"qulūbikum","s":48,"v":12,"w":14,"ri":582,"li":4417},{"id":70662,"a":"وَظَنَنتُمۡ","m":"And you assumed","mi":"dan kamu telah menyangka","mu":"اور گمان کیا تم نے","t":"waẓanantum","s":48,"v":12,"w":15,"ri":913,"li":50},{"id":70663,"a":"ظَنَّ","m":"an assumption","mi":"sangkaan","mu":"گمان","t":"ẓanna","s":48,"v":12,"w":16,"ri":913,"li":2227},{"id":70664,"a":"ٱلسَّوۡءِ","m":"evil","mi":"buruk","mu":"برا","t":"l-sawi","s":48,"v":12,"w":17,"ri":559,"li":3839},{"id":70665,"a":"وَكُنتُمۡ","m":"and you became","mi":"dan kalian","mu":"اور ہو تم","t":"wakuntum","s":48,"v":12,"w":18,"ri":1021,"li":370},{"id":70666,"a":"قَوۡمَۢا","m":"a people","mi":"kaum","mu":"قوم۔ لوگ","t":"qawman","s":48,"v":12,"w":19,"ri":729,"li":1590},{"id":70667,"a":"بُورٗا","m":"ruined","mi":"binasa","mu":"ہلاک ہونے والے","t":"būran","s":48,"v":12,"w":20,"ri":853,"li":3272},{"id":70668,"a":"١٢","m":"(12)","mi":"(12)","mu":"(۱۲)","t":"","s":48,"v":12,"w":21},{"id":70669,"a":"وَمَن","m":"And whoever","mi":"dan barang siapa","mu":"اور جو کوئی","t":"waman","s":48,"v":13,"w":1,"li":477},{"id":70670,"a":"لَّمۡ","m":"(has) not believed","mi":"tidak","mu":"نہ","t":"lam","s":48,"v":13,"w":2,"li":3175},{"id":70671,"a":"يُؤۡمِنۢ","m":"(has) not believed","mi":"beriman","mu":"ایمان لائے","t":"yu'min","s":48,"v":13,"w":3,"ri":537,"li":37}]},{"type":"ayah","line":10,"words":[{"id":70672,"a":"بِٱللَّهِ","m":"in Allah","mi":"kepada Allah","mu":"اللہ پر","t":"bil-lahi","s":48,"v":13,"w":4,"ri":1217,"li":2564},{"id":70673,"a":"وَرَسُولِهِۦ","m":"and His Messenger","mi":"dan rasul-Nya","mu":"اور اس کے رسول پر","t":"warasūlihi","s":48,"v":13,"w":5,"ri":656,"li":610},{"id":70674,"a":"فَإِنَّآ","m":"then indeed, We","mi":"maka sesungguhnya Kami","mu":"تو بیشک ہم نے","t":"fa-innā","s":48,"v":13,"w":6,"li":4098},{"id":70675,"a":"أَعۡتَدۡنَا","m":"[We] have prepared","mi":"Kami menyediakan","mu":"تیار کیا ہم نے","t":"aʿtadnā","s":48,"v":13,"w":7,"ri":1406,"li":1669},{"id":70676,"a":"لِلۡكَٰفِرِينَ","m":"for the disbelievers","mi":"bagi orang-orang kafir","mu":"کافروں کے لیے","t":"lil'kāfirīna","s":48,"v":13,"w":8,"ri":525,"li":795},{"id":70677,"a":"سَعِيرٗا","m":"a Blazing Fire","mi":"neraka yang menyala-nyala","mu":"بھڑکتی ہوئی آگ کو","t":"saʿīran","s":48,"v":13,"w":9,"ri":808,"li":176},{"id":70678,"a":"١٣","m":"(13)","mi":"(13)","mu":"(۱۳)","t":"","s":48,"v":13,"w":10},{"id":70679,"a":"وَلِلَّهِ","m":"And for Allah","mi":"dan kepunyaan Allah","mu":"اور اللہ ہی کے لیے ہے","t":"walillahi","s":48,"v":14,"w":1,"ri":1217,"li":2564},{"id":70680,"a":"مُلۡكُ","m":"(is the) kingdom","mi":"kerajaan","mu":"بادشاہت","t":"mul'ku","s":48,"v":14,"w":2,"ri":1236,"li":1029}]},{"type":"ayah","line":11,"words":[{"id":70681,"a":"ٱلسَّمَٰوَٰتِ","m":"(of) the heavens","mi":"langit(jamak)","mu":"آسمانوں کی","t":"l-samāwāti","s":48,"v":14,"w":3,"ri":462,"li":888},{"id":70682,"a":"وَٱلۡأَرۡضِۚ","m":"and the earth","mi":"dan bumi","mu":"اور زمین کی","t":"wal-arḍi","s":48,"v":14,"w":4,"ri":40,"li":3740},{"id":70683,"a":"يَغۡفِرُ","m":"He forgives","mi":"Dia memberi ampunan","mu":"بخش دے گا","t":"yaghfiru","s":48,"v":14,"w":5,"ri":1260,"li":2556},{"id":70684,"a":"لِمَن","m":"whom","mi":"kepada siapa","mu":"جس کو","t":"liman","s":48,"v":14,"w":6,"li":477},{"id":70685,"a":"يَشَآءُ","m":"He wills","mi":"Dia kehendaki","mu":"وہ چاہے گا","t":"yashāu","s":48,"v":14,"w":7,"ri":1485,"li":4316},{"id":70686,"a":"وَيُعَذِّبُ","m":"and punishes","mi":"dan Dia mengazab","mu":"اور عذاب دے گا","t":"wayuʿadhibu","s":48,"v":14,"w":8,"ri":216,"li":1164},{"id":70687,"a":"مَن","m":"whom","mi":"siapa","mu":"جس کو","t":"man","s":48,"v":14,"w":9,"li":477},{"id":70688,"a":"يَشَآءُۚ","m":"He wills","mi":"Dia kehendaki","mu":"وہ چاہے گا","t":"yashāu","s":48,"v":14,"w":10,"ri":1485,"li":4316}]},{"type":"ayah","line":12,"words":[{"id":70689,"a":"وَكَانَ","m":"And is","mi":"dan adalah","mu":"اور ہے","t":"wakāna","s":48,"v":14,"w":11,"ri":1021,"li":370},{"id":70690,"a":"ٱللَّهُ","m":"Allah","mi":"Allah","mu":"اللہ تعالیٰ","t":"l-lahu","s":48,"v":14,"w":12,"ri":1217,"li":2564},{"id":70691,"a":"غَفُورٗا","m":"Oft-Forgiving","mi":"Maha Pengampun","mu":"غفور","t":"ghafūran","s":48,"v":14,"w":13,"ri":1260,"li":314},{"id":70692,"a":"رَّحِيمٗا","m":"Most Merciful","mi":"Maha Penyayang","mu":"رحیم","t":"raḥīman","s":48,"v":14,"w":14,"ri":1356,"li":1951},{"id":70693,"a":"١٤","m":"(14)","mi":"(14)","mu":"(۱۴)","t":"","s":48,"v":14,"w":15},{"id":70694,"a":"سَيَقُولُ","m":"Will say","mi":"akan berkata","mu":"عنقریب وہ کہیں گے","t":"sayaqūlu","s":48,"v":15,"w":1,"ri":23,"li":1981},{"id":70695,"a":"ٱلۡمُخَلَّفُونَ","m":"those who remained behind","mi":"orang-orang yang tertinggal","mu":"پیچھے چھوڑے جانے والے۔ رہ جانے والے","t":"l-mukhalafūna","s":48,"v":15,"w":2,"ri":1277,"li":3655},{"id":70696,"a":"إِذَا","m":"when","mi":"apabila","mu":"جب","t":"idhā","s":48,"v":15,"w":3,"li":1265}]},{"type":"ayah","line":13,"words":[{"id":70697,"a":"ٱنطَلَقۡتُمۡ","m":"you set forth","mi":"kamu berangkat","mu":"چلو گے تم","t":"inṭalaqtum","s":48,"v":15,"w":4,"ri":1167,"li":3440},{"id":70698,"a":"إِلَىٰ","m":"towards","mi":"kepada","mu":"طرف","t":"ilā","s":48,"v":15,"w":5,"li":3611},{"id":70699,"a":"مَغَانِمَ","m":"(the) spoils of war","mi":"rampasan perang","mu":"غنیمتوں کے","t":"maghānima","s":48,"v":15,"w":6,"ri":572,"li":4535},{"id":70700,"a":"لِتَأۡخُذُوهَا","m":"to take it","mi":"untuk kamu mengambilnya","mu":"تاکہ تم لے سکو ان کو","t":"litakhudhūhā","s":48,"v":15,"w":7,"ri":1182,"li":2403},{"id":70701,"a":"ذَرُونَا","m":"Allow us","mi":"biarkanlah kami","mu":"چھوڑ دو ہم کو","t":"dharūnā","s":48,"v":15,"w":8,"ri":825,"li":275},{"id":70702,"a":"نَتَّبِعۡكُمۡۖ","m":"(to) follow you","mi":"kami mengikuti kamu","mu":"ہم پیروی کریں تمہاری","t":"nattabiʿ'kum","s":48,"v":15,"w":9,"ri":1287,"li":1858},{"id":70703,"a":"يُرِيدُونَ","m":"They wish","mi":"mareka hendak","mu":"وہ چاہتے ہیں","t":"yurīdūna","s":48,"v":15,"w":10,"ri":189,"li":1261}]},{"type":"ayah","line":14,"words":[{"id":70704,"a":"أَن","m":"to","mi":"bahwa","mu":"کہ","t":"an","s":48,"v":15,"w":11,"li":1648},{"id":70705,"a":"يُبَدِّلُواْ","m":"change","mi":"mereka akan mengganti","mu":"وہ بدل ڈالیں","t":"yubaddilū","s":48,"v":15,"w":12,"ri":162,"li":1356},{"id":70706,"a":"كَلَٰمَ","m":"(the) Words","mi":"firman","mu":"کلام","t":"kalāma","s":48,"v":15,"w":13,"ri":1075,"li":630},{"id":70707,"a":"ٱللَّهِۚ","m":"(of) Allah","mi":"Allah","mu":"اللہ کا","t":"l-lahi","s":48,"v":15,"w":14,"ri":1217,"li":2564},{"id":70708,"a":"قُل","m":"Say","mi":"katakanlah","mu":"کہہ دیجیے","t":"qul","s":48,"v":15,"w":15,"ri":23,"li":1981},{"id":70709,"a":"لَّن","m":"Never","mi":"tidak","mu":"ہرگز نہیں","t":"lan","s":48,"v":15,"w":16,"li":2288},{"id":70710,"a":"تَتَّبِعُونَا","m":"will you follow us","mi":"kamu mengikuti kami","mu":"تم پیروی کرو گے ہماری","t":"tattabiʿūnā","s":48,"v":15,"w":17,"ri":1287,"li":1858},{"id":70711,"a":"كَذَٰلِكُمۡ","m":"Thus","mi":"demikianlah","mu":"اسی طرح تمہیں","t":"kadhālikum","s":48,"v":15,"w":18,"li":1167},{"id":70712,"a":"قَالَ","m":"Allah said","mi":"berfirman","mu":"فرمایا","t":"qāla","s":48,"v":15,"w":19,"ri":23,"li":1981},{"id":70713,"a":"ٱللَّهُ","m":"Allah said","mi":"Allah","mu":"اللہ نے","t":"l-lahu","s":48,"v":15,"w":20,"ri":1217,"li":2564},{"id":70714,"a":"مِن","m":"before","mi":"dari","mu":"سے","t":"min","s":48,"v":15,"w":21,"li":477},{"id":70715,"a":"قَبۡلُۖ","m":"before","mi":"sebelum","mu":"اس سے پہلے","t":"qablu","s":48,"v":15,"w":22,"ri":1291,"li":2868}]},{"type":"ayah","line":15,"words":[{"id":70716,"a":"فَسَيَقُولُونَ","m":"Then they will say","mi":"maka akan berkata mereka","mu":"پس عنقریب وہ کہیں گے","t":"fasayaqūlūna","s":48,"v":15,"w":23,"ri":23,"li":1981},{"id":70717,"a":"بَلۡ","m":"Nay","mi":"tetapi","mu":"بلکہ","t":"bal","s":48,"v":15,"w":24,"li":3119},{"id":70718,"a":"تَحۡسُدُونَنَاۚ","m":"you envy us","mi":"kamu dengki pada kami","mu":"تم حسد کرتے ہو ہم سے","t":"taḥsudūnanā","s":48,"v":15,"w":25,"ri":1225},{"id":70719,"a":"بَلۡ","m":"Nay","mi":"tetapi","mu":"نہیں بلکہ","t":"bal","s":48,"v":15,"w":26,"li":3119},{"id":70720,"a":"كَانُواْ","m":"they were","mi":"adalah mereka","mu":"ہیں وہ","t":"kānū","s":48,"v":15,"w":27,"ri":1021,"li":370},{"id":70721,"a":"لَا","m":"not","mi":"tidak","mu":"نہیں","t":"lā","s":48,"v":15,"w":28,"li":3380},{"id":70722,"a":"يَفۡقَهُونَ","m":"understanding","mi":"mereka mengerti","mu":"وہ سمجھتے","t":"yafqahūna","s":48,"v":15,"w":29,"ri":1065,"li":3606},{"id":70723,"a":"إِلَّا","m":"except","mi":"kecuali","mu":"مگر","t":"illā","s":48,"v":15,"w":30,"li":4258},{"id":70724,"a":"قَلِيلٗا","m":"a little","mi":"sedikit","mu":"بہت کم","t":"qalīlan","s":48,"v":15,"w":31,"ri":113,"li":217},{"id":70725,"a":"١٥","m":"(15)","mi":"(15)","mu":"(۱۵)","t":"","s":48,"v":15,"w":32}]}],"surahs":[48]}